viggoprecificacao/__init__.py
viggoprecificacao/_version.py
viggoprecificacao/packages.py
viggoprecificacao/resources.py
viggoprecificacao/subsystem/__init__.py
viggoprecificacao/subsystem/parametrizacao/__init__.py
viggoprecificacao/subsystem/parametrizacao/contrato_viggo/__init__.py
viggoprecificacao/subsystem/parametrizacao/contrato_viggo/controller.py
viggoprecificacao/subsystem/parametrizacao/contrato_viggo/manager.py
viggoprecificacao/subsystem/parametrizacao/contrato_viggo/resource.py
viggoprecificacao/subsystem/parametrizacao/contrato_viggo/router.py
viggoprecificacao/subsystem/parametrizacao/plano_viggo/__init__.py
viggoprecificacao/subsystem/parametrizacao/plano_viggo/controller.py
viggoprecificacao/subsystem/parametrizacao/plano_viggo/manager.py
viggoprecificacao/subsystem/parametrizacao/plano_viggo/resource.py
viggoprecificacao/subsystem/parametrizacao/plano_viggo/router.py
viggoprecificacao/subsystem/parametrizacao/produto_viggo/__init__.py
viggoprecificacao/subsystem/parametrizacao/produto_viggo/manager.py
viggoprecificacao/subsystem/parametrizacao/produto_viggo/resource.py
viggoprecificacao/subsystem/parametrizacao/servico_viggo/__init__.py
viggoprecificacao/subsystem/parametrizacao/servico_viggo/manager.py
viggoprecificacao/subsystem/parametrizacao/servico_viggo/resource.py
viggoprecificacao/subsystem/parametrizacao/termo_aceite_viggo/__init__.py
viggoprecificacao/subsystem/parametrizacao/termo_aceite_viggo/controller.py
viggoprecificacao/subsystem/parametrizacao/termo_aceite_viggo/manager.py
viggoprecificacao/subsystem/parametrizacao/termo_aceite_viggo/resource.py
viggoprecificacao-1.0.21.dist-info/AUTHORS
viggoprecificacao-1.0.21.dist-info/METADATA
viggoprecificacao-1.0.21.dist-info/WHEEL
viggoprecificacao-1.0.21.dist-info/top_level.txt
viggoprecificacao-1.0.21.dist-info/RECORD
