Metadata-Version: 2.1
Name: viggoprecificacao
Version: 1.0.21
Summary: ViggoPrecificacao Backend Flask REST service
Home-page: https://github.com/viggosistemas/viggoprecificacao
License: UNKNOWN
Platform: UNKNOWN
License-File: AUTHORS
Requires-Dist: viggocore<2.0.0,>=1.0.0
Requires-Dist: flask-cors
